{
  "version": null,
  "flags": {},
  "shapes": [
    {
      "line_color": null,
      "fill_color": null,
      "component": [],
      "rotated_box": [],
      "ID": 0,
      "label": "0:gene:ERK1",
      "points": [
        [
          264,
          225
        ],
        [
          349,
          225
        ],
        [
          349,
          245
        ],
        [
          264,
          245
        ]
      ],
      "group_id": null,
      "shape_type": "polygon",
      "flags": {}
    },
    {
      "line_color": null,
      "fill_color": null,
      "component": [],
      "rotated_box": [],
      "ID": 1,
      "label": "1:gene: ETS1",
      "points": [
        [
          371,
          385
        ],
        [
          438,
          385
        ],
        [
          438,
          407
        ],
        [
          371,
          407
        ]
      ],
      "group_id": null,
      "shape_type": "polygon",
      "flags": {}
    }
  ],
  "lineColor": [
    0,
    255,
    0,
    128
  ],
  "fillColor": [
    255,
    0,
    0,
    128
  ],
  "imagePath": "PMC5482458__pone.0179614.g005.jpg",
  "imageData": null,
  "imageHeight": 774,
  "imageWidth": 615
}